edidio_control_py/__init__.py
edidio_control_py/eDS10_ProtocolBuffer_pb2.py
edidio_control_py/exceptions.py
edidio_control_py-0.1.1.dist-info/licenses/LICENSE
edidio_control_py-0.1.1.dist-info/METADATA
edidio_control_py-0.1.1.dist-info/WHEEL
edidio_control_py-0.1.1.dist-info/top_level.txt
edidio_control_py-0.1.1.dist-info/RECORD
